teamscale_client/__init__.py
teamscale_client/client.py
teamscale_client/client_utils.py
teamscale_client/constants.py
teamscale_client/data.py
teamscale_client/teamscale_client_config.py
teamscale_client/teamscale_session.py
teamscale_client/utils.py
teamscale_client-9.2.0.dist-info/LICENSE
teamscale_client-9.2.0.dist-info/METADATA
teamscale_client-9.2.0.dist-info/WHEEL
teamscale_client-9.2.0.dist-info/top_level.txt
teamscale_client-9.2.0.dist-info/RECORD
